lmrp-1.0.13.dist-info/WHEEL
lmrp-1.0.13.dist-info/top_level.txt
lmrp-1.0.13.dist-info/METADATA
lmrp-1.0.13.dist-info/RECORD
lmrp/plots.cpython-36m-x86_64-linux-gnu.so
lmrp/gis_service.cpython-36m-x86_64-linux-gnu.so
lmrp/gis_router.cpython-36m-x86_64-linux-gnu.so
