Metadata-Version: 2.4
Name: lmrp
Version: 1.0.13
Summary: Optimized binary libraries for GIS data fetching and plotting
